pyluhn.py
PyLuhn-0.1.dist-info/METADATA
PyLuhn-0.1.dist-info/RECORD
PyLuhn-0.1.dist-info/WHEEL
PyLuhn-0.1.dist-info/top_level.txt
