Metadata-Version: 2.1
Name: PyLuhn
Version: 0.1
Summary: Basic Implementation for Luhn AlgorithmUseful for Verifying Credit Cards.
Home-page: http://github.com/kadir/pyluhn
Author: Kadir Eksi
Author-email: kadireksi@sabanciuniv.edu
License: Public Domain
Keywords: luhn,check digit,credit card,luhn mod N
Platform: UNKNOWN
Classifier: Programming Language :: Python
Classifier: Intended Audience :: Developers
Classifier: License :: OSI Approved :: MIT License
Classifier: Operating System :: OS Independent
Classifier: Topic :: Software Development :: Libraries :: Python Modules
